vrfy/__init__.py
vrfy/vrfy.py
vrfy/cli/__init__.py
vrfy/cli/vrfyCli.py
vrfy-0.4.0.dist-info/LICENSE
vrfy-0.4.0.dist-info/METADATA
vrfy-0.4.0.dist-info/WHEEL
vrfy-0.4.0.dist-info/entry_points.txt
vrfy-0.4.0.dist-info/top_level.txt
vrfy-0.4.0.dist-info/RECORD
